odoo/addons/mail_filter_adressee_by_contact/README.rst
odoo/addons/mail_filter_adressee_by_contact/__init__.py
odoo/addons/mail_filter_adressee_by_contact/__manifest__.py
odoo/addons/mail_filter_adressee_by_contact/i18n/mail_filter_adressee_by_contact.pot
odoo/addons/mail_filter_adressee_by_contact/models/__init__.py
odoo/addons/mail_filter_adressee_by_contact/models/account_invoice_send.py
odoo/addons/mail_filter_adressee_by_contact/models/mail_compose_message.py
odoo/addons/mail_filter_adressee_by_contact/readme/CONTRIBUTORS.rst
odoo/addons/mail_filter_adressee_by_contact/readme/DESCRIPTION.rst
odoo/addons/mail_filter_adressee_by_contact/static/description/icon.png
odoo/addons/mail_filter_adressee_by_contact/static/description/index.html
odoo/addons/mail_filter_adressee_by_contact/views/mail_compose_message_view.xml
odoo/addons/mail_filter_adressee_by_contact/views/mail_invoice_send_view.xml
odoo14_addon_mail_filter_adressee_by_contact-14.0.1.1.0.dist-info/METADATA
odoo14_addon_mail_filter_adressee_by_contact-14.0.1.1.0.dist-info/WHEEL
odoo14_addon_mail_filter_adressee_by_contact-14.0.1.1.0.dist-info/top_level.txt
odoo14_addon_mail_filter_adressee_by_contact-14.0.1.1.0.dist-info/RECORD
